giturlparse/__init__.py
giturlparse/parser.py
giturlparse/result.py
giturlparse/platforms/__init__.py
giturlparse/platforms/assembla.py
giturlparse/platforms/base.py
giturlparse/platforms/bitbucket.py
giturlparse/platforms/friendcode.py
giturlparse/platforms/github.py
giturlparse/platforms/gitlab.py
giturlparse/tests/__init__.py
giturlparse/tests/test_parse.py
giturlparse/tests/test_rewrite.py
giturlparse-0.13.0.dist-info/licenses/LICENSE
giturlparse-0.13.0.dist-info/METADATA
giturlparse-0.13.0.dist-info/WHEEL
giturlparse-0.13.0.dist-info/top_level.txt
giturlparse-0.13.0.dist-info/RECORD
