Metadata-Version: 2.4
Name: giturlparse
Version: 0.13.0
Summary: A Git URL parsing module (supports parsing and rewriting)
Home-page: https://github.com/nephila/giturlparse
Author: Aaron O Mullan
Author-email: aaron@friendco.de
Maintainer: Iacopo Spalletti
Maintainer-email: i.spalletti@nephila.it
License: Apache v2
Keywords: giturlparse
Classifier: Development Status :: 5 - Production/Stable
Classifier: Framework :: Django
Classifier: Intended Audience :: Developers
Classifier: License :: OSI Approved :: Apache Software License
Classifier: Natural Language :: English
Classifier: Programming Language :: Python :: 3.8
Classifier: Programming Language :: Python :: 3.9
Classifier: Programming Language :: Python :: 3.10
Classifier: Programming Language :: Python :: 3.11
Requires-Python: >=3.8
License-File: LICENSE
Dynamic: license-file
